LICENSE
MANIFEST.in
README.md
setup.py
romspy/__init__.py
romspy/preprocessing.py
romspy/verification.py
romspy.egg-info/PKG-INFO
romspy.egg-info/SOURCES.txt
romspy.egg-info/dependency_links.txt
romspy.egg-info/requires.txt
romspy.egg-info/top_level.txt
romspy/__pycache__/__init__.cpython-36.pyc
romspy/__pycache__/preprocessing.cpython-36.pyc
romspy/__pycache__/verification.cpython-36.pyc
romspy/adjustments/__init__.py
romspy/adjustments/biol.py
romspy/adjustments/clim.py
romspy/adjustments/forcing.py
romspy/adjustments/__pycache__/__init__.cpython-36.pyc
romspy/adjustments/__pycache__/clim.cpython-36.pyc
romspy/adjustments/__pycache__/forcing.cpython-36.pyc
romspy/data_adjustment/__init__.py
romspy/data_adjustment/grb_tools.py
romspy/grid_routines/__init__.py
romspy/grid_routines/grd_to_scrip.py
romspy/grid_routines/__pycache__/__init__.cpython-36.pyc
romspy/grid_routines/__pycache__/grd_to_scrip.cpython-36.pyc
romspy/interpolation/__init__.py
romspy/interpolation/interpolator.py
romspy/interpolation/shift_grid.py
romspy/interpolation/__pycache__/__init__.cpython-36.pyc
romspy/interpolation/__pycache__/interpolator.cpython-36.pyc
romspy/interpolation/__pycache__/shift_grid.cpython-36.pyc
romspy/interpolation/horizontal/__init__.py
romspy/interpolation/horizontal/interpolate.py
romspy/interpolation/horizontal/__pycache__/__init__.cpython-36.pyc
romspy/interpolation/horizontal/__pycache__/interpolate.cpython-36.pyc
romspy/interpolation/vertical/__init__.py
romspy/interpolation/vertical/interpolate.py
romspy/interpolation/vertical/levels.py
romspy/interpolation/vertical/linear.c
romspy/interpolation/vertical/linear.h
romspy/interpolation/vertical/linear.so
romspy/interpolation/vertical/load_c_libs.py
romspy/interpolation/vertical/__pycache__/__init__.cpython-36.pyc
romspy/interpolation/vertical/__pycache__/interpolate.cpython-36.pyc
romspy/interpolation/vertical/__pycache__/levels.cpython-36.pyc
romspy/interpolation/vertical/__pycache__/load_c_libs.cpython-36.pyc