Metadata-Version: 2.1
Name: romspy
Version: 0.9.0
Summary: Preprocessing files for use in ROMS
Home-page: https://https://github.com/Saixos/romspy
Author: Nicolas Munnich
Author-email: nmdm20@bath.ac.uk
License: UNKNOWN
Keywords: preprocessing ROMS roms Regional Ocean Modelling System cdo Climate Data Operators netcdf4
Platform: UNKNOWN
Classifier: Programming Language :: Python :: 3.7
Classifier: License :: OSI Approved :: GNU General Public License v2 or later (GPLv2+)
Classifier: Operating System :: OS Independent
Classifier: Intended Audience :: Science/Research
Classifier: Natural Language :: English
Classifier: Programming Language :: C
Classifier: Topic :: Scientific/Engineering
Classifier: Typing :: Typed
Requires-Python: >=3.6
